first_project/__init__.py
first_project/__main__.py
My_First_Project_19_April_2024-0.0.1.dist-info/METADATA
My_First_Project_19_April_2024-0.0.1.dist-info/WHEEL
My_First_Project_19_April_2024-0.0.1.dist-info/top_level.txt
My_First_Project_19_April_2024-0.0.1.dist-info/RECORD
