Metadata-Version: 2.1
Name: My_First_Project_19_April_2024
Version: 0.0.1
Summary: My first PYPI projects which implements some basic math functions
Author: M S Dheeraj Muthy
Author-email: <ms.dheerajmurthy@iiitb.ac.in>
Keywords: python,basic-math,iiitb
Classifier: Development Status :: 1 - Planning
Classifier: Intended Audience :: Developers
Classifier: Programming Language :: Python :: 3
Classifier: Operating System :: Unix
Classifier: Operating System :: MacOS :: MacOS X
Classifier: Operating System :: Microsoft :: Windows
